Metadata-Version: 1.2
Name: ipcn
Version: 0.1.2
Summary: IP utilities
Home-page: https://github.com/plusplus1/ipcn
Author: plusplus1
Author-email: pror885@163.com
License: UNKNOWN
Platform: UNKNOWN
Classifier: Programming Language :: Python
Classifier: Programming Language :: Python :: 3.6
Requires-Python: >=3.6
